README.txt
setup.cfg
setup.py
BeakerCleanup.egg-info/PKG-INFO
BeakerCleanup.egg-info/SOURCES.txt
BeakerCleanup.egg-info/dependency_links.txt
BeakerCleanup.egg-info/entry_points.txt
BeakerCleanup.egg-info/namespace_packages.txt
BeakerCleanup.egg-info/not-zip-safe
BeakerCleanup.egg-info/requires.txt
BeakerCleanup.egg-info/top_level.txt
beaker/__init__.py
beaker/scripts/__init__.py
beaker/scripts/cleanup.py