Metadata-Version: 1.0
Name: BeakerCleanup
Version: 0.1.2
Summary: A beaker plugin that implements a function to be called from the command line via PasteCall.
Home-page: UNKNOWN
Author: Linas Juskevicius
Author-email: linas@idiles.com
License: MIT
Keywords: beaker session database cleanup sqlalchemy delete old
Platform: UNKNOWN
